schema_checker/__init__.py
schema_checker/extras.py
schema_checker/jschema.py
tests/__init__.py
tests/extras.py
tests/jschema.py
schema_checker-1.1.1.dist-info/LICENSE
schema_checker-1.1.1.dist-info/METADATA
schema_checker-1.1.1.dist-info/WHEEL
schema_checker-1.1.1.dist-info/top_level.txt
schema_checker-1.1.1.dist-info/RECORD
