Metadata-Version: 2.1
Name: schema-checker
Version: 1.1.1
Summary: Another schema validator :)
Home-page: https://github.com/moff4/schema_schecker
Author: Komissarov Andrey
Author-email: Komissar.off.andrey@gmail.com
License: UNKNOWN
Platform: UNKNOWN
Classifier: Programming Language :: Python :: 3
Classifier: Operating System :: OS Independent
